gsclinks/__init__.py
gsclinks/links.py
gsclinks/utils.py
gsclinks-1.0.5.dist-info/LICENSE
gsclinks-1.0.5.dist-info/METADATA
gsclinks-1.0.5.dist-info/WHEEL
gsclinks-1.0.5.dist-info/top_level.txt
gsclinks-1.0.5.dist-info/RECORD
