Metadata-Version: 2.1
Name: gsclinks
Version: 1.0.5
Summary: Scrape backlink data from Google Search Console
Home-page: https://github.com/tranngocminhhieu/google-search-console-links
Author: Tran Ngoc Minh Hieu
Author-email: tnmhieu@gmail.com
License-File: LICENSE
Requires-Dist: beautifulsoup4
Requires-Dist: requests
Requires-Dist: tqdm
